LICENSE
README.md
setup.py
pypi_scraper/__init__.py
tribunnews_scraper.egg-info/PKG-INFO
tribunnews_scraper.egg-info/SOURCES.txt
tribunnews_scraper.egg-info/dependency_links.txt
tribunnews_scraper.egg-info/requires.txt
tribunnews_scraper.egg-info/top_level.txt